<Properties>
  <MonoDevelop.Ide.DebuggingService.Breakpoints>
    <BreakpointStore />
  </MonoDevelop.Ide.DebuggingService.Breakpoints>
  <MonoDevelop.Ide.Workspace ActiveConfiguration="Debug" />
  <MultiItemStartupConfigurations />
  <MonoDevelop.Ide.DebuggingService.PinnedWatches />
  <MonoDevelop.Ide.Workbench ActiveDocument="VNLibrary/Script/VNChapter.cs">
    <Files>
      <File FileName="VNLibrary/Script/VNScript.cs" Line="49" Column="11" />
      <File FileName="VNLibrary/VNUtil/VNUtil_Parse.cs" Line="15" Column="4" />
      <File FileName="VNLibrary/Script/Command.cs" Line="4" Column="36" NotebookId="1" />
      <File FileName="VNLibrary/Script/VNChapter.cs" Line="12" Column="4" NotebookId="1" />
      <File FileName="VNLibrary/Script/ScriptProvider.cs" Line="6" Column="44" NotebookId="1" />
      <File FileName="VNLibrary/Script/ScriptCommand/ScriptCommad.cs" Line="11" Column="49" NotebookId="1" />
      <File FileName="VNLibrary/VNParser/IVNParsable.cs" Line="6" Column="22" NotebookId="1" />
    </Files>
    <Pads>
      <Pad Id="ProjectPad">
        <State name="__root__">
          <Node name="VNLibrary" expanded="True">
            <Node name="VNLibrary" expanded="True">
              <Node name="VNParser" expanded="True" />
              <Node name="VNUtil" expanded="True" />
            </Node>
          </Node>
        </State>
      </Pad>
    </Pads>
  </MonoDevelop.Ide.Workbench>
</Properties>